README.md
setup.cfg
setup.py
pyunraid/__init__.py
pyunraid/constants.py
pyunraid/containers.py
pyunraid/disks.py
pyunraid/exceptions.py
pyunraid/helpers.py
pyunraid/notifications.py
pyunraid/plugins.py
pyunraid/shares.py
pyunraid/unraid.py
pyunraid/users.py
pyunraid/vms.py
pyunraid.egg-info/PKG-INFO
pyunraid.egg-info/SOURCES.txt
pyunraid.egg-info/dependency_links.txt
pyunraid.egg-info/requires.txt
pyunraid.egg-info/top_level.txt
pyunraid/models/__init__.py
pyunraid/models/container.py
pyunraid/models/disk.py
pyunraid/models/model.py
pyunraid/models/notification.py
pyunraid/models/plugin.py
pyunraid/models/setting.py
pyunraid/models/share.py
pyunraid/models/user.py
pyunraid/models/vm.py